setup.py
data_pre.egg-info/PKG-INFO
data_pre.egg-info/SOURCES.txt
data_pre.egg-info/dependency_links.txt
data_pre.egg-info/requires.txt
data_pre.egg-info/top_level.txt
pre/__init__.py
pre/pd_check.py
pre/pd_data.py
pre/pd_error.py
pre/pd_params.py
pre/pd_utils.py
pre_csv/__init__.py
pre_csv/pd_csv.py
pre_excel/__init__.py
pre_excel/pd_excel.py
pre_json/__init__.py
pre_json/pd_json.py
pre_pickle/__init__.py
pre_pickle/pd_pickle.py
pre_test/__init__.py
pre_test/pre_test.py