Metadata-Version: 1.0
Name: data-pre
Version: 0.2.4
Summary: pandas data preprocessing tool
Home-page: https://github.com/ftconan/data_pre.git
Author: magician
Author-email: ftconan@163.com
License: UNKNOWN
Platform: any
